dg_zoo_server/__init__.py
dg_zoo_server/args.py
dg_zoo_server/dev_list.py
dg_zoo_server/internals.py
dg_zoo_server/main.py
dg_zoo_server/public_router.py
dg_zoo_server-0.3.0.dist-info/METADATA
dg_zoo_server-0.3.0.dist-info/WHEEL
dg_zoo_server-0.3.0.dist-info/entry_points.txt
dg_zoo_server-0.3.0.dist-info/top_level.txt
dg_zoo_server-0.3.0.dist-info/RECORD
