Metadata-Version: 2.1
Name: dg_zoo_server
Version: 0.3.0
Requires-Dist: fastapi<1.0,>=0.114.1
Requires-Dist: uvicorn<1.0,>=0.30.6
Requires-Dist: pydantic<3.0,>=2.9.1
Requires-Dist: aiorwlock<2.0,>=1.4.0
Requires-Dist: aiofiles<25.0,>=24.1.0
Requires-Dist: base58<3.0,>=2.1.1
Requires-Dist: python-multipart<1.0,>=0.0.9
Provides-Extra: build
Requires-Dist: fastapi<1.0,>=0.114.1; extra == "build"
Requires-Dist: uvicorn<1.0,>=0.30.6; extra == "build"
Requires-Dist: pydantic<3.0,>=2.9.1; extra == "build"
Requires-Dist: aiorwlock<2.0,>=1.4.0; extra == "build"
Requires-Dist: aiofiles<25.0,>=24.1.0; extra == "build"
Requires-Dist: base58<3.0,>=2.1.1; extra == "build"
Requires-Dist: python-multipart<1.0,>=0.0.9; extra == "build"
Requires-Dist: build<2.0,>=1.2.2; extra == "build"
Requires-Dist: pytest<9.0,>=8.3.3; extra == "build"
Requires-Dist: coverage<8.0,>=7.6.1; extra == "build"
Requires-Dist: httpx<1.0,>=0.27.2; extra == "build"
Requires-Dist: mypy<2.0,>=1.11.2; extra == "build"
Requires-Dist: flake8<8.0,>=7.1.1; extra == "build"
